{"pageProps":{"project":{"id":"4","title":"Mother Of Dragons","bio":"This assignment was created for learning to work in group.","creationDate":"2018-11-28","headImage":{"url":"https://res.cloudinary.com/eva1999/image/upload/v1601468545/1839876_Mac_Book_Pro_on_table_ea2b1abe21.png","caption":""},"images":[],"vids":[{"url":"https://res.cloudinary.com/eva1999/video/upload/v1601468281/got_85b2cef152.mp4","caption":""}],"categories":[{"id":"2","name":"Development"}],"team":"Danielle Terras \nEva Denys","client":null,"tools":"Phaser 3, PHP","link":null,"briefing":null,"goal":null,"download":[]}},"__N_SSG":true}